{"zone":[{"zone_id":"1360","country_id":"91","name":"Bafata Region","code":"BF","status":"1"},{"zone_id":"1361","country_id":"91","name":"Biombo Region","code":"BB","status":"1"},{"zone_id":"1362","country_id":"91","name":"Bissau Region","code":"BS","status":"1"},{"zone_id":"1363","country_id":"91","name":"Bolama Region","code":"BL","status":"1"},{"zone_id":"1364","country_id":"91","name":"Cacheu Region","code":"CA","status":"1"},{"zone_id":"1365","country_id":"91","name":"Gabu Region","code":"GA","status":"1"},{"zone_id":"1366","country_id":"91","name":"Oio Region","code":"OI","status":"1"},{"zone_id":"1367","country_id":"91","name":"Quinara Region","code":"QU","status":"1"},{"zone_id":"1368","country_id":"91","name":"Tombali Region","code":"TO","status":"1"}],"country_id":"91","name":"Guinea-Bissau","iso_code_2":"GW","iso_code_3":"GNB","address_format_id":"1","postcode_required":"0","status":"1"}