{"zone":[{"zone_id":"2679","country_id":"175","name":"Alba","code":"AB","status":"1"},{"zone_id":"2680","country_id":"175","name":"Arad","code":"AR","status":"1"},{"zone_id":"2681","country_id":"175","name":"Arge\u0219","code":"AG","status":"1"},{"zone_id":"2682","country_id":"175","name":"Bac\u0103u","code":"BC","status":"1"},{"zone_id":"2683","country_id":"175","name":"Bihor","code":"BH","status":"1"},{"zone_id":"2684","country_id":"175","name":"Bistri\u021ba-N\u0103s\u0103ud","code":"BN","status":"1"},{"zone_id":"2685","country_id":"175","name":"Boto\u0219ani","code":"BT","status":"1"},{"zone_id":"2687","country_id":"175","name":"Br\u0103ila","code":"BR","status":"1"},{"zone_id":"2686","country_id":"175","name":"Bra\u0219ov","code":"BV","status":"1"},{"zone_id":"2688","country_id":"175","name":"Bucure\u0219ti","code":"B","status":"1"},{"zone_id":"2689","country_id":"175","name":"Buz\u0103u","code":"BZ","status":"1"},{"zone_id":"2691","country_id":"175","name":"C\u0103l\u0103ra\u0219i","code":"CL","status":"1"},{"zone_id":"2690","country_id":"175","name":"Cara\u0219-Severin","code":"CS","status":"1"},{"zone_id":"2692","country_id":"175","name":"Cluj","code":"CJ","status":"1"},{"zone_id":"2693","country_id":"175","name":"Constan\u021ba","code":"CT","status":"1"},{"zone_id":"2694","country_id":"175","name":"Covasna","code":"CV","status":"1"},{"zone_id":"2695","country_id":"175","name":"D\u00e2mbovi\u021ba","code":"DB","status":"1"},{"zone_id":"2696","country_id":"175","name":"Dolj","code":"DJ","status":"1"},{"zone_id":"2697","country_id":"175","name":"Gala\u021bi","code":"GL","status":"1"},{"zone_id":"2698","country_id":"175","name":"Giurgiu","code":"GR","status":"1"},{"zone_id":"2699","country_id":"175","name":"Gorj","code":"GJ","status":"1"},{"zone_id":"2700","country_id":"175","name":"Harghita","code":"HR","status":"1"},{"zone_id":"2701","country_id":"175","name":"Hunedoara","code":"HD","status":"1"},{"zone_id":"2702","country_id":"175","name":"Ialomi\u021ba","code":"IL","status":"1"},{"zone_id":"2703","country_id":"175","name":"Ia\u0219i","code":"IS","status":"1"},{"zone_id":"2704","country_id":"175","name":"Ilfov","code":"IF","status":"1"},{"zone_id":"2705","country_id":"175","name":"Maramure\u0219","code":"MM","status":"1"},{"zone_id":"2706","country_id":"175","name":"Mehedin\u021bi","code":"MH","status":"1"},{"zone_id":"2707","country_id":"175","name":"Mure\u0219","code":"MS","status":"1"},{"zone_id":"2708","country_id":"175","name":"Neam\u021b","code":"NT","status":"1"},{"zone_id":"2709","country_id":"175","name":"Olt","code":"OT","status":"1"},{"zone_id":"2710","country_id":"175","name":"Prahova","code":"PH","status":"1"},{"zone_id":"2712","country_id":"175","name":"S\u0103laj","code":"SJ","status":"1"},{"zone_id":"2711","country_id":"175","name":"Satu-Mare","code":"SM","status":"1"},{"zone_id":"2713","country_id":"175","name":"Sibiu","code":"SB","status":"1"},{"zone_id":"2714","country_id":"175","name":"Suceava","code":"SV","status":"1"},{"zone_id":"2715","country_id":"175","name":"Teleorman","code":"TR","status":"1"},{"zone_id":"2716","country_id":"175","name":"Timi\u0219","code":"TM","status":"1"},{"zone_id":"2717","country_id":"175","name":"Tulcea","code":"TL","status":"1"},{"zone_id":"2719","country_id":"175","name":"V\u00e2lcea","code":"VL","status":"1"},{"zone_id":"2718","country_id":"175","name":"Vaslui","code":"VS","status":"1"},{"zone_id":"2720","country_id":"175","name":"Vrancea","code":"VN","status":"1"}],"country_id":"175","name":"Rom\u00e2nia","iso_code_2":"RO","iso_code_3":"ROM","address_format_id":"1","postcode_required":"0","status":"1"}