{"country_id":"62","iso_code_2":"EC","iso_code_3":"ECU","address_format_id":"1","postcode_required":"0","status":"1","language_id":"1","name":"Ecuador","zone":[{"zone_id":"979","country_id":"62","code":"AZU","status":"1","language_id":"1","name":"Azuay","country":"Ecuador"},{"zone_id":"980","country_id":"62","code":"BOL","status":"1","language_id":"1","name":"Bolivar","country":"Ecuador"},{"zone_id":"981","country_id":"62","code":"CAN","status":"1","language_id":"1","name":"Ca&ntilde;ar","country":"Ecuador"},{"zone_id":"982","country_id":"62","code":"CAR","status":"1","language_id":"1","name":"Carchi","country":"Ecuador"},{"zone_id":"983","country_id":"62","code":"CHI","status":"1","language_id":"1","name":"Chimborazo","country":"Ecuador"},{"zone_id":"984","country_id":"62","code":"COT","status":"1","language_id":"1","name":"Cotopaxi","country":"Ecuador"},{"zone_id":"985","country_id":"62","code":"EOR","status":"1","language_id":"1","name":"El Oro","country":"Ecuador"},{"zone_id":"986","country_id":"62","code":"ESM","status":"1","language_id":"1","name":"Esmeraldas","country":"Ecuador"},{"zone_id":"987","country_id":"62","code":"GPS","status":"1","language_id":"1","name":"Gal&aacute;pagos","country":"Ecuador"},{"zone_id":"988","country_id":"62","code":"GUA","status":"1","language_id":"1","name":"Guayas","country":"Ecuador"},{"zone_id":"989","country_id":"62","code":"IMB","status":"1","language_id":"1","name":"Imbabura","country":"Ecuador"},{"zone_id":"990","country_id":"62","code":"LOJ","status":"1","language_id":"1","name":"Loja","country":"Ecuador"},{"zone_id":"991","country_id":"62","code":"LRO","status":"1","language_id":"1","name":"Los Rios","country":"Ecuador"},{"zone_id":"992","country_id":"62","code":"MAN","status":"1","language_id":"1","name":"Manab&iacute;","country":"Ecuador"},{"zone_id":"993","country_id":"62","code":"MSA","status":"1","language_id":"1","name":"Morona Santiago","country":"Ecuador"},{"zone_id":"994","country_id":"62","code":"NAP","status":"1","language_id":"1","name":"Napo","country":"Ecuador"},{"zone_id":"995","country_id":"62","code":"ORE","status":"1","language_id":"1","name":"Orellana","country":"Ecuador"},{"zone_id":"996","country_id":"62","code":"PAS","status":"1","language_id":"1","name":"Pastaza","country":"Ecuador"},{"zone_id":"997","country_id":"62","code":"PIC","status":"1","language_id":"1","name":"Pichincha","country":"Ecuador"},{"zone_id":"998","country_id":"62","code":"SUC","status":"1","language_id":"1","name":"Sucumb&iacute;os","country":"Ecuador"},{"zone_id":"999","country_id":"62","code":"TUN","status":"1","language_id":"1","name":"Tungurahua","country":"Ecuador"},{"zone_id":"1000","country_id":"62","code":"ZCH","status":"1","language_id":"1","name":"Zamora Chinchipe","country":"Ecuador"}]}