{"country_id":"13","iso_code_2":"AU","iso_code_3":"AUS","address_format_id":"1","postcode_required":"0","status":"1","language_id":"1","name":"Australia","zone":[{"zone_id":"191","country_id":"13","code":"ACT","status":"1","language_id":"1","name":"Australian Capital Territory","country":"Australia"},{"zone_id":"192","country_id":"13","code":"NSW","status":"1","language_id":"1","name":"New South Wales","country":"Australia"},{"zone_id":"193","country_id":"13","code":"NT","status":"1","language_id":"1","name":"Northern Territory","country":"Australia"},{"zone_id":"194","country_id":"13","code":"QLD","status":"1","language_id":"1","name":"Queensland","country":"Australia"},{"zone_id":"195","country_id":"13","code":"SA","status":"1","language_id":"1","name":"South Australia","country":"Australia"},{"zone_id":"196","country_id":"13","code":"TAS","status":"1","language_id":"1","name":"Tasmania","country":"Australia"},{"zone_id":"197","country_id":"13","code":"VIC","status":"1","language_id":"1","name":"Victoria","country":"Australia"},{"zone_id":"198","country_id":"13","code":"WA","status":"1","language_id":"1","name":"Western Australia","country":"Australia"}]}