{"country_id":"9","iso_code_2":"AG","iso_code_3":"ATG","address_format_id":"1","postcode_required":"0","status":"1","language_id":"1","name":"Antigua and Barbuda","zone":[{"zone_id":"153","country_id":"9","code":"BAR","status":"1","language_id":"1","name":"Barbuda","country":"Antigua and Barbuda"},{"zone_id":"154","country_id":"9","code":"RED","status":"1","language_id":"1","name":"Redonda","country":"Antigua and Barbuda"},{"zone_id":"147","country_id":"9","code":"ASG","status":"1","language_id":"1","name":"Saint George","country":"Antigua and Barbuda"},{"zone_id":"148","country_id":"9","code":"ASJ","status":"1","language_id":"1","name":"Saint John","country":"Antigua and Barbuda"},{"zone_id":"149","country_id":"9","code":"ASM","status":"1","language_id":"1","name":"Saint Mary","country":"Antigua and Barbuda"},{"zone_id":"150","country_id":"9","code":"ASL","status":"1","language_id":"1","name":"Saint Paul","country":"Antigua and Barbuda"},{"zone_id":"151","country_id":"9","code":"ASR","status":"1","language_id":"1","name":"Saint Peter","country":"Antigua and Barbuda"},{"zone_id":"152","country_id":"9","code":"ASH","status":"1","language_id":"1","name":"Saint Philip","country":"Antigua and Barbuda"}]}